nonebot_plugin_eitherchoice-0.2.0.post1.dist-info/METADATA
nonebot_plugin_eitherchoice-0.2.0.post1.dist-info/WHEEL
nonebot_plugin_eitherchoice-0.2.0.post1.dist-info/licenses/LICENSE
nonebot_plugin_eitherchoice/__init__.py
nonebot_plugin_eitherchoice/__main__.py
nonebot_plugin_eitherchoice/config.py
nonebot_plugin_eitherchoice/data_source.py
nonebot_plugin_eitherchoice/res/template.html.jinja
nonebot_plugin_eitherchoice-0.2.0.post1.dist-info/RECORD
