Metadata-Version: 2.1
Name: nonebot-plugin-eitherchoice
Version: 0.2.0.post1
Summary: Let AI help you compare two things.
Home-page: https://github.com/lgc-NB2Dev/nonebot-plugin-eitherchoice
Author-Email: student_2333 <lgc2333@126.com>
License: MIT
Project-URL: Homepage, https://github.com/lgc-NB2Dev/nonebot-plugin-eitherchoice
Requires-Python: <4.0,>=3.8
Requires-Dist: nonebot2>=2.1.1
Requires-Dist: nonebot-plugin-htmlrender>=0.2.1
Requires-Dist: nonebot-plugin-send-anything-anywhere>=0.3.2
Requires-Dist: pydantic>=1.10.4
Requires-Dist: httpx[http2]>=0.24.1
Requires-Dist: beautifulsoup4>=4.12.2
Requires-Dist: lxml>=4.9.3
